fastapi_tools/__init__.py
fastapi_tools/metrics.py
fastapi_tools/router.py
fastapi_tools/auth/__init__.py
fastapi_tools/auth/_core/__init__.py
fastapi_tools/auth/_core/adapter.py
fastapi_tools/auth/_core/bearer.py
fastapi_tools/auth/_core/types.py
fastapi_tools/auth/auth0/__init__.py
fastapi_tools/auth/auth0/bearer.py
fastapi_tools/auth/auth0/token.py
fastapi_tools/auth/cognito/__init__.py
fastapi_tools/auth/cognito/bearer.py
fastapi_tools/auth/cognito/token.py
fastapi_tools/auth/okta/__init__.py
fastapi_tools/auth/okta/bearer.py
fastapi_tools/auth/okta/token.py
fastapi_tools/data/mutable.py
fastapi_tools/depends/__init__.py
fastapi_tools/depends/access.py
fastapi_tools/depends/query.py
fastapi_tools/depends/state.py
fastapi_tools/mongo/__init__.py
fastapi_tools/mongo/adapter.py
fastapi_tools/mongo/client.py
fastapi_tools/mongo/depends.py
fastapi_tools/mongo/document.py
fastapi_tools/mongo/object_id.py
fastapi_tools/schema/__init__.py
fastapi_tools/schema/crud.py
fastapi_tools/schema/types.py
fastapi_tools/schema/util.py
fastapi_tools/util/__init__.py
fastapi_tools/util/httpx_util.py
fastapi_tools/util/jwt_util.py
nydev_fastapi_tools-0.0.1.dist-info/METADATA
nydev_fastapi_tools-0.0.1.dist-info/WHEEL
nydev_fastapi_tools-0.0.1.dist-info/top_level.txt
nydev_fastapi_tools-0.0.1.dist-info/RECORD
