Metadata-Version: 2.1
Name: nydev-fastapi-tools
Version: 0.0.1
Summary: FastAPI integrations for Auth0, Okta, and MongoDB Atlas
Author-email: Rajan Khullar <rkhullar03@gmail.com>
License: MIT NON-AI License
Project-URL: Repository, https://github.com/rkhullar/python-libraries/tree/main/fastapi-tools
Keywords: fastapi,mongodb,atlas,auth0,okta,cognito,aws
Requires-Python: >=3.10
Requires-Dist: httpx
Requires-Dist: fastapi
Requires-Dist: pydantic-settings
Provides-Extra: lambda
Requires-Dist: mangum ; extra == 'lambda'
Provides-Extra: mongodb
Requires-Dist: pymongo[aws,srv] ; extra == 'mongodb'
Provides-Extra: server
Requires-Dist: uvicorn ; extra == 'server'
